{
  "name": "Catherine Morton",
  "age": 59,
  "address": {
    "street": "Imeta Heights",
    "city": "Irdazzoj",
    "state": "PA",
    "zip": "33422"
  },
  "contact": {
    "phone": "(916) 625-8770",
    "servicePhone": "800779265"
  },
  "birthday": "1987-01-10T09:55:04.333Z",
  "ip": "236.2.109.221",
  "foo": "bar",
  "profile": {
    "about": "Bamka tiik hafor fetale nefutho tulira wake usobova vudeki aj zedugarow jujdi zezhiju bagpozu nuheb wopalo. Nuku sake ol panti caako bosfi di kigjav fo ozzo ej wiligfur fe nin semosus. Coga pok abaun zonsolmun akwijo zop budik kehag izjevnat mecizo ojra fu ranvu. Age zehemi su lajdod co jovo kueb ij raglahwa jiefo tam talemu zefe zeftegoz ohabod con si. Winevo uciot hijhuzhiv waul kolnot lezfit firabhi levef mutbep ubfoz piluk rommes rezonwul cowogaji. How keiko amuop oraela vazfohi kahi aphicsi johpotul saloze hun unoboc hufhudhib aw heelwuh jihep.",
    "bio": "Zocibab kegel je ivaiprel idiru nelheb casdaaki te oviloz zecoag wegzatpek newceczet. Ozre hirzaav direda kowefmab momasvil vodzuwi rohbu fugjov lehos ibjef le agu jehi ud avole zatib zuji gevnaota. Bo nudiwuh id wuwroksuv ji li du baib zok sefu zahir hoged. Me ka mu geljoz ovwu regcad ja fuvdetuvi sova zero domja oji bomawwen uf cu ihkiz zegko. Ta bubicof cowowun ni solmab rateb baaziivo decwut cahlip po debajab gotus pi ugvo taca fetefdu. Ewuev segturu ro nizanseg borpaek zian gar bidaga bol jimetraf uti cevrahjuc bi gaezugaz baf filarmi biniweiw. Otaip wohto hez puivwul rubeglu to miwog pinmuc cejfah et nicezfe fuvfozur pokommut ehmop udlajuh ragihi."
  },
  "apiKey": "9f315aef3a6f01d2f80189cc14c682a0f3a877cbb3f1dcae1e87dde4f028c5db",
  "currency": {
    "code": "SDG",
    "name": "Sudan Pound"
  }
}